tarsus/__init__.py
tarsus/client.py
tarsus_client_generated/.gitignore
tarsus_client_generated/README.md
tarsus_client_generated/__init__.py
tarsus_client_generated/client.py
tarsus_client_generated/errors.py
tarsus_client_generated/pyproject.toml
tarsus_client_generated/types.py
tarsus_client_generated/api/__init__.py
tarsus_client_generated/api/admin_dashboard/__init__.py
tarsus_client_generated/api/admin_dashboard/export_report_api_v1_backend_admin_reports_export_get.py
tarsus_client_generated/api/admin_dashboard/get_system_stats_api_v1_backend_admin_system_stats_get.py
tarsus_client_generated/api/admin_dashboard/get_tenant_details_api_v1_backend_admin_tenants_tenant_id_get.py
tarsus_client_generated/api/admin_dashboard/get_tenant_usage_api_v1_backend_admin_tenants_tenant_id_usage_get.py
tarsus_client_generated/api/admin_dashboard/list_all_tenants_api_v1_backend_admin_tenants_get.py
tarsus_client_generated/api/api_keys/__init__.py
tarsus_client_generated/api/api_keys/create_api_key_api_v1_backend_api_keys_post.py
tarsus_client_generated/api/api_keys/delete_api_key_api_v1_backend_api_keys_key_id_delete.py
tarsus_client_generated/api/api_keys/get_endpoint_definitions_api_v1_backend_api_keys_endpoints_definitions_get.py
tarsus_client_generated/api/api_keys/list_api_keys_api_v1_backend_api_keys_get.py
tarsus_client_generated/api/api_keys/regenerate_api_key_api_v1_backend_api_keys_key_id_regenerate_post.py
tarsus_client_generated/api/api_keys/update_api_key_api_v1_backend_api_keys_key_id_patch.py
tarsus_client_generated/api/api_usage/__init__.py
tarsus_client_generated/api/api_usage/get_usage_logs_api_v1_backend_usage_logs_get.py
tarsus_client_generated/api/api_usage/get_usage_stats_api_v1_backend_usage_stats_get.py
tarsus_client_generated/api/auth/__init__.py
tarsus_client_generated/api/auth/forgot_password_api_v1_auth_forgot_password_post.py
tarsus_client_generated/api/auth/google_login_root_api_v1_auth_google_post.py
tarsus_sdk-0.1.1.dist-info/METADATA
tarsus_sdk-0.1.1.dist-info/WHEEL
tarsus_sdk-0.1.1.dist-info/RECORD
